cz_emoji.py
cz_emoji-0.4.0.dist-info/LICENSE
cz_emoji-0.4.0.dist-info/WHEEL
cz_emoji-0.4.0.dist-info/METADATA
cz_emoji-0.4.0.dist-info/RECORD
